rezip.py
rezip-0.5.2.dist-info/LICENSE.rst
rezip-0.5.2.dist-info/METADATA
rezip-0.5.2.dist-info/WHEEL
rezip-0.5.2.dist-info/entry_points.txt
rezip-0.5.2.dist-info/top_level.txt
rezip-0.5.2.dist-info/RECORD
