Metadata-Version: 2.1
Name: rezip
Version: 0.5.2
Summary: Repack ZIP archives
Home-page: https://gitlab.com/dfritzsche/python-rezip
Maintainer: David Fritzsche
Maintainer-email: david.fritzsche@mvua.de
License: MIT
Platform: any
Classifier: Intended Audience :: Developers
Classifier: License :: OSI Approved :: MIT License
Classifier: Operating System :: OS Independent
Classifier: Topic :: Utilities
Classifier: Programming Language :: Python :: 3 :: Only
Classifier: Programming Language :: Python :: 3.6
Classifier: Programming Language :: Python :: 3.7
Classifier: Typing :: Typed
Requires-Python: >=3.6
